{
  "name": "space-science-pack",
  "module": {
    "user": {
      "structures": [
        {
          "recipe": {
            "name": "space-science-pack",
            "modules": {}
          }
        },
        {
          "recipe": {
            "name": "iron-plate",
            "modules": {}
          }
        },
        {
          "recipe": {
            "name": "metallic-asteroid-crushing",
            "modules": {}
          }
        },
        {
          "recipe": {
            "name": "carbonic-asteroid-crushing",
            "modules": {}
          }
        },
        {
          "recipe": {
            "name": "oxide-asteroid-crushing",
            "modules": {}
          }
        }
      ]
    }
  }
}